atlas/__init__.py
atlas/atlas.py
atlas/lib/__init__.py
atlas/lib/atl_importer.py
atlas/lib/core.py
atlas/lib/error.py
atlas/lib/executor.py
atlas/lib/expect.py
atlas/lib/linker_loader.py
atlas/lib/screen.py
docs/source/conf.py
malware_atlas-0.2.15.dist-info/METADATA
malware_atlas-0.2.15.dist-info/WHEEL
malware_atlas-0.2.15.dist-info/entry_points.txt
malware_atlas-0.2.15.dist-info/licenses/AUTHORS
malware_atlas-0.2.15.dist-info/licenses/LICENSE
malware_atlas-0.2.15.dist-info/RECORD
