Metadata-Version: 2.1
Name: malware-atlas
Version: 0.2.15
Summary: ATLAS - Malware Analysis Description
Project-URL: Homepage, https://github.com/malware-atlas/atlas
Author: Mert Degirmenci
License: MIT License
License-File: AUTHORS
License-File: LICENSE
Keywords: atlas,malware,threat
Classifier: License :: OSI Approved :: MIT License
Classifier: Programming Language :: Python
Classifier: Programming Language :: Python :: 3
Requires-Python: >=3.6
Requires-Dist: pyyaml
Requires-Dist: requests
Requires-Dist: tomli; python_version < '3.11'
Provides-Extra: dev
Requires-Dist: python-magic; extra == 'dev'
